jydwd/__init__.py
jydwd/client.py
jydwd/jydwd.py
jydwd-0.16.dist-info/LICENSE
jydwd-0.16.dist-info/METADATA
jydwd-0.16.dist-info/WHEEL
jydwd-0.16.dist-info/entry_points.txt
jydwd-0.16.dist-info/top_level.txt
jydwd-0.16.dist-info/RECORD
