Metadata-Version: 2.1
Name: jydwd
Version: 0.16
Summary: A small example package
Home-page: https://github.com/pypa/sampleproject
Author: jiangyd
Author-email: 962584902@qq.com
License: MIT License
Keywords: jydwd
Platform: any
Classifier: Programming Language :: Python :: 3
Classifier: License :: OSI Approved :: MIT License
Classifier: Operating System :: OS Independent
Requires-Dist: requests (>=2.23.0)
